epydemic/__init__.py
epydemic/adddelete.py
epydemic/bbt.py
epydemic/compartmentedmodel.py
epydemic/coreperiphery_generator.py
epydemic/drawset.py
epydemic/generator.py
epydemic/loci.py
epydemic/modular_generator.py
epydemic/monitor.py
epydemic/networkdynamics.py
epydemic/networkexperiment.py
epydemic/newmanziff.py
epydemic/nz_extended.py
epydemic/opinion_model.py
epydemic/percolate.py
epydemic/plc_generator.py
epydemic/process.py
epydemic/processsequence.py
epydemic/pulsecoupled.py
epydemic/py.typed
epydemic/seir_model.py
epydemic/shuffle.py
epydemic/sir_model.py
epydemic/sir_model_fixed_recovery.py
epydemic/sir_model_variable_infection.py
epydemic/sirs_model.py
epydemic/sis_model.py
epydemic/sis_model_fixed_recovery.py
epydemic/sivr_model.py
epydemic/standard_generators.py
epydemic/statistics.py
epydemic/stochasticdynamics.py
epydemic/synchronousdynamics.py
epydemic/types.py
epydemic/vaccinate_model.py
epydemic/gf/__init__.py
epydemic/gf/continuous_gf.py
epydemic/gf/discrete_gf.py
epydemic/gf/function_gf.py
epydemic/gf/gf.py
epydemic/gf/interface.py
epydemic/gf/product_gf.py
epydemic/gf/standard_gfs.py
epydemic/gf/sum_gf.py
epydemic-1.14.1.dist-info/LICENSE
epydemic-1.14.1.dist-info/METADATA
epydemic-1.14.1.dist-info/WHEEL
epydemic-1.14.1.dist-info/top_level.txt
epydemic-1.14.1.dist-info/RECORD
