Metadata-Version: 2.1
Name: epydemic
Version: 1.14.1
Summary: Epidemic network simulations in Python
Home-page: http://github.com/simoninireland/epydemic
Author: Simon Dobson
Author-email: simoninireland@gmail.com
License: License :: OSI Approved :: GNU General Public License v3 (GPLv3)
Classifier: Development Status :: 4 - Beta
Classifier: Intended Audience :: Science/Research
Classifier: Intended Audience :: Developers
Classifier: Programming Language :: Python :: 3.6
Classifier: Programming Language :: Python :: 3.7
Classifier: Programming Language :: Python :: 3.8
Classifier: Programming Language :: Python :: 3.9
Classifier: Programming Language :: Python :: 3.10
Classifier: Topic :: Scientific/Engineering
Requires-Python: >=3.6
License-File: LICENSE
Requires-Dist: networkx>=2.4
Requires-Dist: epyc>=1.7.2
Requires-Dist: pandas
Requires-Dist: numpy>=1.18
Requires-Dist: scipy
Requires-Dist: mpmath
Requires-Dist: python-dotenv
Requires-Dist: epydemicarchive-client
